[
  {
    "translations": {
      "item": [
        {
          "original": "concept album",
          "translated": "概念专辑"
        },
        {
          "original": "double album",
          "translated": "双专辑"
        },
        {
          "original": "live album",
          "translated": "现场专辑"
        },
        {
          "original": "photo album",
          "translated": "相册"
        },
        {
          "original": "tribute album",
          "translated": "致敬专辑"
        },
        {
          "original": "compilation",
          "translated": "合辑"
        },
        {
          "original": "anthology",
          "translated": "精选集"
        },
        {
          "original": "Albula",
          "translated": "阿尔布拉"
        },
        {
          "original": "Albumblatt",
          "translated": "专辑页"
        }
      ]
    }
  },
  0
]