[
  {
    "translations": {
      "item": [
        {
          "original": "restfulness",
          "translated": "宁静"
        },
        {
          "original": "quiet",
          "translated": "安静"
        },
        {
          "original": "serenity",
          "translated": "宁静"
        },
        {
          "original": "sereneness",
          "translated": "宁静"
        },
        {
          "original": "quietness",
          "translated": "寂静"
        },
        {
          "original": "tranquillity",
          "translated": "宁静"
        },
        {
          "original": "call-waiting",
          "translated": "呼叫等待"
        },
        {
          "original": "calmative",
          "translated": "镇静剂"
        },
        {
          "original": "balm",
          "translated": "香脂"
        },
        {
          "original": "bom",
          "translated": "物料清单"
        },
        {
          "original": "bomb",
          "translated": "炸弹"
        },
        {
          "original": "dom",
          "translated": "领域"
        },
        {
          "original": "halm",
          "translated": "茎秆"
        },
        {
          "original": "hom",
          "translated": "同源"
        },
        {
          "original": "malm",
          "translated": "软泥灰岩"
        },
        {
          "original": "mam",
          "translated": "妈妈"
        },
        {
          "original": "mom",
          "translated": "妈妈"
        },
        {
          "original": "palm",
          "translated": "手掌"
        },
        {
          "original": "pom",
          "translated": "聚甲醛"
        },
        {
          "original": "pomme",
          "translated": "苹果"
        }
      ]
    }
  },
  0
]