[
  {
    "translations": {
      "item": [
        {
          "original": "metaphor",
          "translated": "隐喻"
        },
        {
          "original": "concede defeat",
          "translated": "认输"
        },
        {
          "original": "conceited",
          "translated": "自负的"
        },
        {
          "original": "amit",
          "translated": "阿米特"
        },
        {
          "original": "athlete",
          "translated": "运动员"
        },
        {
          "original": "backseat",
          "translated": "后座"
        },
        {
          "original": "blackfeet",
          "translated": "黑脚族"
        },
        {
          "original": "broadsheet",
          "translated": "对开报纸"
        },
        {
          "original": "browbeat",
          "translated": "恫吓"
        },
        {
          "original": "buckwheat",
          "translated": "荞麦"
        },
        {
          "original": "compete",
          "translated": "竞争"
        },
        {
          "original": "compleat",
          "translated": "完美的"
        },
        {
          "original": "complete",
          "translated": "完成"
        },
        {
          "original": "concrete",
          "translated": "混凝土"
        },
        {
          "original": "crabmeat",
          "translated": "蟹肉"
        }
      ]
    }
  },
  0
]