[
  {
    "translations": {
      "item": [
        {
          "original": "decolonize",
          "translated": "非殖民化"
        },
        {
          "original": "acclimatisation",
          "translated": "适应环境"
        },
        {
          "original": "acclimatization",
          "translated": "适应环境"
        },
        {
          "original": "acidification",
          "translated": "酸化"
        },
        {
          "original": "actualization",
          "translated": "实现"
        },
        {
          "original": "annualization",
          "translated": "年化"
        },
        {
          "original": "autocorrelation",
          "translated": "自相关"
        },
        {
          "original": "autoregulation",
          "translated": "自动调节"
        },
        {
          "original": "beatification",
          "translated": "宣福"
        },
        {
          "original": "beneficiation",
          "translated": "选矿"
        },
        {
          "original": "biodegradation",
          "translated": "生物降解"
        },
        {
          "original": "biotransformation",
          "translated": "生物转化"
        },
        {
          "original": "bureaucratization",
          "translated": "官僚化"
        }
      ]
    }
  },
  0
]