[
  {
    "translations": {
      "item": [
        {
          "original": "certainly",
          "translated": "当然"
        },
        {
          "original": "surely",
          "translated": "无疑"
        },
        {
          "original": "sure",
          "translated": "确定"
        },
        {
          "original": "clearly",
          "translated": "清楚地"
        },
        {
          "original": "probably",
          "translated": "可能"
        },
        {
          "original": "really",
          "translated": "确实"
        },
        {
          "original": "definite integration",
          "translated": "定积分"
        },
        {
          "original": "definite quadratic form",
          "translated": "定二次型"
        },
        {
          "original": "indefinitely",
          "translated": "无限期地"
        }
      ]
    }
  },
  0
]