[
  {
    "translations": {
      "item": [
        {
          "original": "downsun",
          "translated": "逆光"
        },
        {
          "original": "Down syndrome",
          "translated": "唐氏综合征"
        },
        {
          "original": "bowstring",
          "translated": "弓弦"
        },
        {
          "original": "coiling",
          "translated": "盘绕"
        },
        {
          "original": "drawstring",
          "translated": "束带"
        },
        {
          "original": "forewing",
          "translated": "前翅"
        },
        {
          "original": "hamstring",
          "translated": "腿筋"
        },
        {
          "original": "lapwing",
          "translated": "凤头麦鸡"
        },
        {
          "original": "mainspring",
          "translated": "主发条"
        },
        {
          "original": "offspring",
          "translated": "后代"
        },
        {
          "original": "plaything",
          "translated": "玩物"
        },
        {
          "original": "shoestring",
          "translated": "鞋带"
        },
        {
          "original": "texting",
          "translated": "发短信"
        },
        {
          "original": "upswing",
          "translated": "上升"
        }
      ]
    }
  },
  0
]