[
  {
    "translations": {
      "item": [
        {
          "original": "eager beaver",
          "translated": "积极分子"
        },
        {
          "original": "excited",
          "translated": "兴奋的"
        },
        {
          "original": "enthusiastic",
          "translated": "热情的"
        },
        {
          "original": "avid",
          "translated": "热衷的"
        },
        {
          "original": "anxious",
          "translated": "焦虑的"
        },
        {
          "original": "keen",
          "translated": "敏锐的"
        },
        {
          "original": "Eagan",
          "translated": "伊根"
        },
        {
          "original": "eager beaver",
          "translated": "积极分子"
        },
        {
          "original": "leaguer",
          "translated": "联盟成员"
        },
        {
          "original": "meager",
          "translated": "贫乏的"
        },
        {
          "original": "meagre",
          "translated": "贫乏的"
        },
        {
          "original": "segar",
          "translated": "雪茄"
        }
      ]
    }
  },
  0
]