[
  {
    "translations": {
      "item": [
        {
          "original": "gender euphoria",
          "translated": "性别愉悦"
        },
        {
          "original": "ecstasy",
          "translated": "狂喜"
        },
        {
          "original": "joy",
          "translated": "喜悦"
        },
        {
          "original": "elation",
          "translated": "兴高采烈"
        },
        {
          "original": "happiness",
          "translated": "幸福"
        },
        {
          "original": "heaven",
          "translated": "天堂"
        },
        {
          "original": "euphorbium",
          "translated": "大戟"
        },
        {
          "original": "euphoriant",
          "translated": "致欣快剂"
        },
        {
          "original": "chorea",
          "translated": "舞蹈病"
        },
        {
          "original": "correa",
          "translated": "科雷亚"
        },
        {
          "original": "doria",
          "translated": "多利亚"
        },
        {
          "original": "gloria",
          "translated": "荣耀颂"
        },
        {
          "original": "scoria",
          "translated": "炉渣"
        },
        {
          "original": "shorea",
          "translated": "娑罗树属"
        },
        {
          "original": "thoria",
          "translated": "二氧化 thorium"
        },
        {
          "original": "aporia",
          "translated": "疑难"
        },
        {
          "original": "centaurea",
          "translated": "矢车菊属"
        },
        {
          "original": "dysphoria",
          "translated": "烦躁不安"
        },
        {
          "original": "septoria",
          "translated": "壳针孢属"
        },
        {
          "original": "signoria",
          "translated": "领主统治"
        }
      ]
    }
  },
  0
]