[
  {
    "translations": {
      "item": [
        {
          "original": "change a flat",
          "translated": "换轮胎"
        },
        {
          "original": "change a (flat) tire",
          "translated": "换轮胎"
        },
        {
          "original": "European flat",
          "translated": "欧洲扁平"
        },
        {
          "original": "European flat oyster",
          "translated": "欧洲扁蚝"
        },
        {
          "original": "fall flat",
          "translated": "彻底失败"
        },
        {
          "original": "flat as a pancake",
          "translated": "扁平如煎饼"
        },
        {
          "original": "flat battery",
          "translated": "电池没电"
        },
        {
          "original": "flat broke",
          "translated": "身无分文"
        },
        {
          "original": "flat iron",
          "translated": "熨斗"
        },
        {
          "original": "flat on one's back",
          "translated": "仰卧"
        },
        {
          "original": "flat out",
          "translated": "竭尽全力"
        },
        {
          "original": "flat race",
          "translated": "平地赛跑"
        },
        {
          "original": "flat tax",
          "translated": "单一税"
        },
        {
          "original": "granny flat",
          "translated": "祖母房"
        },
        {
          "original": "in nothing flat",
          "translated": "立刻"
        },
        {
          "original": "exact",
          "translated": "精确的"
        },
        {
          "original": "round",
          "translated": "圆的"
        },
        {
          "original": "flasque",
          "translated": "扁平的"
        },
        {
          "original": "flat advertising rate",
          "translated": "统一广告费率"
        },
        {
          "original": "bat",
          "translated": "蝙蝠"
        },
        {
          "original": "batt",
          "translated": "板条"
        },
        {
          "original": "brat",
          "translated": "顽童"
        },
        {
          "original": "cat",
          "translated": "猫"
        },
        {
          "original": "chat",
          "translated": "聊天"
        },
        {
          "original": "fat",
          "translated": "脂肪"
        },
        {
          "original": "gat",
          "translated": "手枪"
        },
        {
          "original": "gnat",
          "translated": "小蚊子"
        },
        {
          "original": "hat",
          "translated": "帽子"
        },
        {
          "original": "kat",
          "translated": "卡特"
        },
        {
          "original": "mat",
          "translated": "垫子"
        }
      ]
    }
  },
  0
]