[
  {
    "translations": {
      "item": [
        {
          "original": "valiant",
          "translated": "英勇的"
        },
        {
          "original": "courageous",
          "translated": "勇敢的"
        },
        {
          "original": "brave",
          "translated": "勇敢的"
        },
        {
          "original": "heroical",
          "translated": "英雄的"
        },
        {
          "original": "heroic",
          "translated": "英雄的"
        },
        {
          "original": "fearless",
          "translated": "无畏的"
        },
        {
          "original": "gallanilide",
          "translated": "镓苯胺"
        },
        {
          "original": "talent",
          "translated": "才能"
        },
        {
          "original": "valent",
          "translated": "化合价的"
        },
        {
          "original": "topgallant",
          "translated": "上桅帆"
        }
      ]
    }
  },
  0
]