[
  {
    "translations": {
      "item": [
        {
          "original": "bode ill",
          "translated": "预示厄运"
        },
        {
          "original": "for good and for ill",
          "translated": "无论好坏"
        },
        {
          "original": "house of ill repute",
          "translated": "妓院"
        },
        {
          "original": "ill afford",
          "translated": "难以承受"
        },
        {
          "original": "ill at ease",
          "translated": "不安"
        },
        {
          "original": "ill effects",
          "translated": "不良影响"
        },
        {
          "original": "ill repute",
          "translated": "坏名声"
        },
        {
          "original": "ill will",
          "translated": "恶意"
        },
        {
          "original": "physically ill",
          "translated": "身体不适"
        },
        {
          "original": "terminally ill",
          "translated": "绝症"
        },
        {
          "original": "violently ill",
          "translated": "病得很重"
        },
        {
          "original": "woman of ill repute",
          "translated": "名声不好的女人"
        },
        {
          "original": "sick",
          "translated": "生病的"
        },
        {
          "original": "ilka day",
          "translated": "每天"
        },
        {
          "original": "bill",
          "translated": "账单"
        },
        {
          "original": "brill",
          "translated": "多宝鱼"
        },
        {
          "original": "chill",
          "translated": "寒意"
        },
        {
          "original": "drill",
          "translated": "钻头"
        },
        {
          "original": "fil",
          "translated": "文件"
        },
        {
          "original": "fill",
          "translated": "填充"
        },
        {
          "original": "frill",
          "translated": "褶边"
        },
        {
          "original": "gill",
          "translated": "鳃"
        },
        {
          "original": "grill",
          "translated": "烤架"
        },
        {
          "original": "grille",
          "translated": "格栅"
        },
        {
          "original": "jill",
          "translated": "杰尔"
        },
        {
          "original": "kill",
          "translated": "杀死"
        }
      ]
    }
  },
  0
]