[
  {
    "translations": {
      "item": [
        {
          "original": "microelectromechanical",
          "translated": "微机电"
        },
        {
          "original": "microelectrophoresis",
          "translated": "微电泳"
        },
        {
          "original": "optoelectronics",
          "translated": "光电子学"
        },
        {
          "original": "avionics",
          "translated": "航空电子学"
        },
        {
          "original": "electronics",
          "translated": "电子学"
        },
        {
          "original": "histrionics",
          "translated": "表演艺术"
        },
        {
          "original": "hydroponics",
          "translated": "水培法"
        },
        {
          "original": "nucleonics",
          "translated": "核子学"
        },
        {
          "original": "ultrasonics",
          "translated": "超声学"
        },
        {
          "original": "conics",
          "translated": "圆锥曲线学"
        },
        {
          "original": "onyx",
          "translated": "缟玛瑙"
        },
        {
          "original": "phonics",
          "translated": "语音学"
        },
        {
          "original": "sonics",
          "translated": "声学"
        },
        {
          "original": "tonics",
          "translated": "补药"
        }
      ]
    }
  },
  0
]