[
  {
    "translations": {
      "item": [
        {
          "original": "bordeaux mixture",
          "translated": "波尔多液"
        },
        {
          "original": "cough mixture",
          "translated": "止咳合剂"
        },
        {
          "original": "mixture stop",
          "translated": "混合物停止"
        },
        {
          "original": "mix",
          "translated": "混合"
        },
        {
          "original": "blend",
          "translated": "混合"
        },
        {
          "original": "amalgam",
          "translated": "汞合金"
        },
        {
          "original": "amalgamation",
          "translated": "合并"
        },
        {
          "original": "alloy",
          "translated": "合金"
        },
        {
          "original": "combination",
          "translated": "组合"
        },
        {
          "original": "mixtion",
          "translated": "混合"
        },
        {
          "original": "mixture stop",
          "translated": "混合物停止"
        },
        {
          "original": "fixture",
          "translated": "固定装置"
        },
        {
          "original": "admixture",
          "translated": "掺合物"
        },
        {
          "original": "intermixture",
          "translated": "混杂物"
        }
      ]
    }
  },
  0
]