[
  {
    "translations": {
      "item": [
        {
          "original": "have none of",
          "translated": "不接受；不容忍"
        },
        {
          "original": "none but",
          "translated": "只有；除…之外谁也不"
        },
        {
          "original": "none of one's beeswax",
          "translated": "不关某人的事"
        },
        {
          "original": "none of someone's concern",
          "translated": "不关某人的事"
        },
        {
          "original": "none of the above",
          "translated": "以上皆非"
        },
        {
          "original": "none of your business",
          "translated": "不关你的事"
        },
        {
          "original": "none other than",
          "translated": "正是；不是别人，正是"
        },
        {
          "original": "none the",
          "translated": "一点也不"
        },
        {
          "original": "none the wiser",
          "translated": "一无所知；一点也不明白"
        },
        {
          "original": "none the worse for wear",
          "translated": "毫发无损；完好无损"
        },
        {
          "original": "none too",
          "translated": "一点也不；并非很"
        },
        {
          "original": "none too pleased",
          "translated": "很不高兴"
        },
        {
          "original": "none too soon",
          "translated": "再快也不为过；早就该如此"
        },
        {
          "original": "second to none",
          "translated": "首屈一指；无与伦比"
        },
        {
          "original": "slim to none",
          "translated": "微乎其微；几乎没有"
        },
        {
          "original": "nobody",
          "translated": "没有人；无名小卒"
        },
        {
          "original": "nondurables",
          "translated": "非耐用品"
        },
        {
          "original": "nonearning",
          "translated": "无收益的；不赚钱的"
        },
        {
          "original": "bun",
          "translated": "小圆面包；发髻"
        },
        {
          "original": "done",
          "translated": "完成的；做完的"
        },
        {
          "original": "dun",
          "translated": "灰褐色的；催债"
        },
        {
          "original": "fun",
          "translated": "乐趣；娱乐"
        },
        {
          "original": "gun",
          "translated": "枪；炮"
        },
        {
          "original": "hun",
          "translated": "匈奴人"
        },
        {
          "original": "jun",
          "translated": "六月（缩写）"
        },
        {
          "original": "nun",
          "translated": "修女；尼姑"
        },
        {
          "original": "one",
          "translated": "一；一个"
        },
        {
          "original": "pun",
          "translated": "双关语"
        },
        {
          "original": "run",
          "translated": "跑；运行"
        },
        {
          "original": "shun",
          "translated": "避开；回避"
        }
      ]
    }
  },
  0
]