[
  {
    "translations": {
      "item": [
        {
          "original": "nouns look like adjectives but they're not",
          "translated": "名词看起来像形容词但它们不是"
        },
        {
          "original": "collective noun",
          "translated": "集体名词"
        },
        {
          "original": "common noun",
          "translated": "普通名词"
        },
        {
          "original": "count noun",
          "translated": "可数名词"
        },
        {
          "original": "mass noun",
          "translated": "物质名词"
        },
        {
          "original": "noncount noun",
          "translated": "不可数名词"
        },
        {
          "original": "noun phrase",
          "translated": "名词短语"
        },
        {
          "original": "proper noun",
          "translated": "专有名词"
        },
        {
          "original": "verbal noun",
          "translated": "动名词"
        },
        {
          "original": "can be replaced with a pronoun",
          "translated": "可以用代词替换"
        },
        {
          "original": "and refer to an entity",
          "translated": "并指代一个实体"
        },
        {
          "original": "school bus",
          "translated": "校车"
        },
        {
          "original": "noumenon",
          "translated": "本体"
        },
        {
          "original": "nounal",
          "translated": "名词性的"
        },
        {
          "original": "bown",
          "translated": "弓"
        },
        {
          "original": "clown",
          "translated": "小丑"
        },
        {
          "original": "crown",
          "translated": "王冠"
        },
        {
          "original": "drown",
          "translated": "淹死"
        },
        {
          "original": "frown",
          "translated": "皱眉"
        },
        {
          "original": "gown",
          "translated": "礼服"
        },
        {
          "original": "lown",
          "translated": "低声"
        },
        {
          "original": "town",
          "translated": "城镇"
        },
        {
          "original": "adown",
          "translated": "向下"
        },
        {
          "original": "blowdown",
          "translated": "吹倒"
        },
        {
          "original": "breakdown",
          "translated": "故障"
        },
        {
          "original": "countdown",
          "translated": "倒计时"
        }
      ]
    }
  },
  0
]