[
  {
    "translations": {
      "item": [
        {
          "original": "such as plutocracy",
          "translated": "例如财阀统治"
        },
        {
          "original": "oligarchic",
          "translated": "寡头政治的"
        },
        {
          "original": "oligidic",
          "translated": "少糖的"
        },
        {
          "original": "hierarchy",
          "translated": "等级制度"
        },
        {
          "original": "matriarchy",
          "translated": "母系社会"
        },
        {
          "original": "patriarchy",
          "translated": "父权制"
        },
        {
          "original": "arche",
          "translated": "始基"
        },
        {
          "original": "sparky",
          "translated": "活泼的"
        },
        {
          "original": "autarky",
          "translated": "经济自给自足"
        },
        {
          "original": "menarche",
          "translated": "初潮"
        }
      ]
    }
  },
  0
]