[
  {
    "translations": {
      "item": [
        {
          "original": "parenesis",
          "translated": "劝诫"
        },
        {
          "original": "parentage",
          "translated": "出身"
        },
        {
          "original": "errant",
          "translated": "犯错误的"
        },
        {
          "original": "aberrant",
          "translated": "异常的"
        },
        {
          "original": "apparent",
          "translated": "明显的"
        },
        {
          "original": "declarant",
          "translated": "申报人"
        },
        {
          "original": "grandparent",
          "translated": "祖父母"
        },
        {
          "original": "stepparent",
          "translated": "继父母"
        },
        {
          "original": "transparent",
          "translated": "透明的"
        },
        {
          "original": "semitransparent",
          "translated": "半透明的"
        }
      ]
    }
  },
  0
]