[
  {
    "translations": {
      "item": [
        {
          "original": "sociable weaverbird",
          "translated": "群居织巢鸟"
        },
        {
          "original": "outgoing",
          "translated": "外向的"
        },
        {
          "original": "social",
          "translated": "社交的"
        },
        {
          "original": "hospitable",
          "translated": "好客的"
        },
        {
          "original": "friendly",
          "translated": "友好的"
        },
        {
          "original": "sociability",
          "translated": "合群性"
        },
        {
          "original": "sociable weaverbird",
          "translated": "群居织巢鸟"
        },
        {
          "original": "negotiable",
          "translated": "可协商的"
        },
        {
          "original": "unsociable",
          "translated": "不爱交际的"
        },
        {
          "original": "nonnegotiable",
          "translated": "不可协商的"
        }
      ]
    }
  },
  0
]