[
  {
    "translations": {
      "item": [
        {
          "original": "adjust",
          "translated": "调整"
        },
        {
          "original": "adapt",
          "translated": "适应"
        },
        {
          "original": "suit",
          "translated": "适合"
        },
        {
          "original": "conform",
          "translated": "符合"
        },
        {
          "original": "put",
          "translated": "放置"
        },
        {
          "original": "customize",
          "translated": "定制"
        },
        {
          "original": "tail of the eye",
          "translated": "眼角"
        },
        {
          "original": "bailer",
          "translated": "戽斗"
        },
        {
          "original": "bailor",
          "translated": "保释人"
        },
        {
          "original": "baler",
          "translated": "打包机"
        },
        {
          "original": "jailer",
          "translated": "狱卒"
        },
        {
          "original": "jailor",
          "translated": "狱卒"
        },
        {
          "original": "paler",
          "translated": "更苍白的"
        },
        {
          "original": "sailer",
          "translated": "帆船"
        },
        {
          "original": "sailor",
          "translated": "水手"
        },
        {
          "original": "scalar",
          "translated": "标量"
        },
        {
          "original": "scaler",
          "translated": "定标器"
        },
        {
          "original": "trailer",
          "translated": "拖车"
        },
        {
          "original": "whaler",
          "translated": "捕鲸船"
        }
      ]
    }
  },
  0
]