[
  {
    "translations": {
      "item": [
        {
          "original": "temporary",
          "translated": "临时的"
        },
        {
          "original": "arbitrarily",
          "translated": "任意地"
        },
        {
          "original": "customarily",
          "translated": "习惯上"
        },
        {
          "original": "militarily",
          "translated": "军事上"
        },
        {
          "original": "momentarily",
          "translated": "片刻地"
        },
        {
          "original": "necessarily",
          "translated": "必然地"
        },
        {
          "original": "ordinarily",
          "translated": "通常地"
        },
        {
          "original": "secondarily",
          "translated": "次要地"
        },
        {
          "original": "voluntarily",
          "translated": "自愿地"
        },
        {
          "original": "airily",
          "translated": "轻快地"
        },
        {
          "original": "caroli",
          "translated": "卡罗利"
        },
        {
          "original": "merrily",
          "translated": "欢乐地"
        },
        {
          "original": "verily",
          "translated": "确实地"
        }
      ]
    }
  },
  0
]