[
  {
    "translations": {
      "item": [
        {
          "original": "less than thrilled",
          "translated": "不太高兴"
        },
        {
          "original": "thrilled to bits",
          "translated": "非常高兴"
        },
        {
          "original": "thrill",
          "translated": "激动"
        },
        {
          "original": "thrilled to bits",
          "translated": "非常兴奋"
        },
        {
          "original": "backfilled",
          "translated": "回填"
        },
        {
          "original": "distilled",
          "translated": "蒸馏"
        },
        {
          "original": "fulfilled",
          "translated": "实现"
        },
        {
          "original": "infilled",
          "translated": "填充"
        },
        {
          "original": "instilled",
          "translated": "灌输"
        },
        {
          "original": "rebuild",
          "translated": "重建"
        },
        {
          "original": "refilled",
          "translated": "重新填充"
        },
        {
          "original": "unfilled",
          "translated": "未填充"
        },
        {
          "original": "unskilled",
          "translated": "不熟练的"
        },
        {
          "original": "untilled",
          "translated": "未耕种的"
        },
        {
          "original": "billed",
          "translated": "开账单"
        },
        {
          "original": "build",
          "translated": "建造"
        }
      ]
    }
  },
  0
]