[
  {
    "translations": {
      "item": [
        {
          "original": "valet de chambre",
          "translated": "贴身男仆"
        },
        {
          "original": "valet parking",
          "translated": "代客泊车"
        },
        {
          "original": "valet service",
          "translated": "代客服务"
        },
        {
          "original": "valeryl",
          "translated": "戊酰基"
        },
        {
          "original": "valet de chambre",
          "translated": "贴身男仆"
        },
        {
          "original": "airway",
          "translated": "呼吸道"
        },
        {
          "original": "allay",
          "translated": "减轻"
        },
        {
          "original": "archway",
          "translated": "拱道"
        },
        {
          "original": "array",
          "translated": "数组"
        },
        {
          "original": "ashtray",
          "translated": "烟灰缸"
        },
        {
          "original": "astray",
          "translated": "迷路"
        },
        {
          "original": "aue",
          "translated": "奥厄"
        },
        {
          "original": "away",
          "translated": "离开"
        },
        {
          "original": "ballet",
          "translated": "芭蕾舞"
        },
        {
          "original": "belay",
          "translated": "系住"
        },
        {
          "original": "beltway",
          "translated": "环城公路"
        },
        {
          "original": "beret",
          "translated": "贝雷帽"
        }
      ]
    }
  },
  0
]